bulk_python/__init__.py
bulk_python/command.py
bulk_python/configs/default.json
bulk_python/configs/help.txt
bulk_python/help.py
bulk_python/init.py
bulk_python/install.py
bulk_python/main.py
bulk_python/run.py
bulk_python/uninstall.py
bulk_python-0.1.5.dist-info/entry_points.txt
bulk_python-0.1.5.dist-info/LICENSE
bulk_python-0.1.5.dist-info/METADATA
bulk_python-0.1.5.dist-info/WHEEL
bulk_python-0.1.5.dist-info/RECORD
