Metadata-Version: 2.1
Name: bulk-python
Version: 0.1.5
Summary: Bulk helps you declare, manage and install dependencies of Python projects.
License: MIT
Author: Oguntunde Caleb Fiyinfoluwa
Author-email: oasis.mystre@gmail.com
Requires-Python: >=3.11,<4.0
Classifier: License :: OSI Approved :: MIT License
Classifier: Programming Language :: Python :: 3
Classifier: Programming Language :: Python :: 3.11
